<annotation>
	<folder>collectedimages</folder>
	<filename>a.c7a8486f-9b9a-11ec-aaf7-d481d788f76c.jpg</filename>
	<path>C:\Users\Kazi Dev\Untitled Folder\images\collectedimages\a.c7a8486f-9b9a-11ec-aaf7-d481d788f76c.jpg</path>
	<source>
		<database>Unknown</database>
	</source>
	<size>
		<width>640</width>
		<height>480</height>
		<depth>3</depth>
	</size>
	<segmented>0</segmented>
	<object>
		<name>a</name>
		<pose>Unspecified</pose>
		<truncated>1</truncated>
		<difficult>0</difficult>
		<bndbox>
			<xmin>117</xmin>
			<ymin>168</ymin>
			<xmax>448</xmax>
			<ymax>480</ymax>
		</bndbox>
	</object>
</annotation>
